<annotation>
	<folder>image_vehicle_truck</folder>
	<filename>20232_225.jpg</filename>
	<path>C:\Users\levie\OneDrive\Desktop\300_bus\image_vehicle_truck\20232_225.jpg</path>
	<source>
		<database>Unknown</database>
	</source>
	<size>
		<width>512</width>
		<height>288</height>
		<depth>3</depth>
	</size>
	<segmented>0</segmented>
	<object>
		<name>motorbike</name>
		<pose>Unspecified</pose>
		<truncated>0</truncated>
		<difficult>0</difficult>
		<bndbox>
			<xmin>159</xmin>
			<ymin>147</ymin>
			<xmax>188</xmax>
			<ymax>181</ymax>
		</bndbox>
	</object>
	<object>
		<name>motorbike</name>
		<pose>Unspecified</pose>
		<truncated>0</truncated>
		<difficult>0</difficult>
		<bndbox>
			<xmin>359</xmin>
			<ymin>205</ymin>
			<xmax>398</xmax>
			<ymax>276</ymax>
		</bndbox>
	</object>
	<object>
		<name>car</name>
		<pose>Unspecified</pose>
		<truncated>0</truncated>
		<difficult>0</difficult>
		<bndbox>
			<xmin>308</xmin>
			<ymin>155</ymin>
			<xmax>362</xmax>
			<ymax>208</ymax>
		</bndbox>
	</object>
	<object>
		<name>car</name>
		<pose>Unspecified</pose>
		<truncated>0</truncated>
		<difficult>0</difficult>
		<bndbox>
			<xmin>344</xmin>
			<ymin>85</ymin>
			<xmax>362</xmax>
			<ymax>109</ymax>
		</bndbox>
	</object>
	<object>
		<name>car</name>
		<pose>Unspecified</pose>
		<truncated>0</truncated>
		<difficult>0</difficult>
		<bndbox>
			<xmin>147</xmin>
			<ymin>102</ymin>
			<xmax>214</xmax>
			<ymax>133</ymax>
		</bndbox>
	</object>
</annotation>
